cython_lint/__init__.py
cython_lint/cython_lint.py
cython_lint/string_fixer.py
cython_lint-0.19.0.dist-info/METADATA
cython_lint-0.19.0.dist-info/WHEEL
cython_lint-0.19.0.dist-info/entry_points.txt
cython_lint-0.19.0.dist-info/licenses/LICENSE
cython_lint-0.19.0.dist-info/RECORD
