Metadata-Version: 2.4
Name: cython-lint
Version: 0.19.0
Summary: Lint Cython files
Project-URL: Homepage, https://github.com/MarcoGorelli/cython-lint
Project-URL: Bug Tracker, https://github.com/MarcoGorelli/cython-lint
Author-email: Marco Gorelli <33491632+MarcoGorelli@users.noreply.github.com>
License-File: LICENSE
Classifier: License :: OSI Approved :: MIT License
Classifier: Operating System :: OS Independent
Classifier: Programming Language :: Python :: 3
Requires-Python: >=3.10
Requires-Dist: cython>=0.29.32
Requires-Dist: pycodestyle
Requires-Dist: tokenize-rt>=3.2.0
Requires-Dist: tomli; python_version < '3.11'
